naas_proxy_manager/ProxyManager.py
naas_proxy_manager/ProxyManager_test.py
naas_proxy_manager/__init__.py
naas_proxy_manager/classes/IProxy.py
naas_proxy_manager/classes/IProxyProvider.py
naas_proxy_manager/classes/IProxyType.py
naas_proxy_manager/classes/Provider.py
naas_proxy_manager/classes/ProxyStatus.py
naas_proxy_manager/classes/ProxyType.py
naas_proxy_manager/classes/__init__.py
naas_proxy_manager/providers/__init__.py
naas_proxy_manager/providers/aws/AWSEC2Proxy.py
naas_proxy_manager/providers/aws/AWSEC2Proxy_test.py
naas_proxy_manager/providers/aws/AWSProvider.py
naas_proxy_manager/providers/aws/AWSProvider_test.py
naas_proxy_manager/providers/aws/AWSProxyType.py
naas_proxy_manager/providers/aws/AWSSquidProxy.py
naas_proxy_manager/providers/aws/AWSSquidProxy_test.py
naas_proxy_manager/providers/aws/__init__.py
naas_proxy_manager-1.3.0.dist-info/METADATA
naas_proxy_manager-1.3.0.dist-info/WHEEL
naas_proxy_manager-1.3.0.dist-info/top_level.txt
naas_proxy_manager-1.3.0.dist-info/RECORD
