Metadata-Version: 2.1
Name: naas-proxy-manager
Version: 1.3.0
Summary: Create proxies on multiple providers with ease.
Home-page: https://github.com/jupyter-naas/naas-proxy-manager
Author: Maxime Jublou
Author-email: maxime@naas.ai
Maintainer: Maxime Jublou
Maintainer-email: maxime@naas.ai
License: UNKNOWN
Keywords: proxy,aws,providers,automated
Platform: UNKNOWN
Requires-Dist: boto3 (~=1.26)
Requires-Dist: loguru (~=0.6)
Requires-Dist: pydash (~=5.1)
Requires-Dist: requests (~=2.28)
